wxmarkdown/__init__.py
wxmarkdown/extended_rtc.py
wxmarkdown/markdown.py
wxMarkdown-1.0.0.post1.dist-info/LICENSE
wxMarkdown-1.0.0.post1.dist-info/METADATA
wxMarkdown-1.0.0.post1.dist-info/WHEEL
wxMarkdown-1.0.0.post1.dist-info/top_level.txt
wxMarkdown-1.0.0.post1.dist-info/RECORD
