Metadata-Version: 2.1
Name: wxMarkdown
Version: 1.0.0.post1
Summary: Write formatted text for wxPython in Markdown.
Author-email: Maximillian Strand <maxi@millian.se>
License: MIT License (MIT)
Project-URL: Repository, https://gitlab.com/deepadmax/wxMarkdown
Requires-Python: >=3.10
License-File: LICENSE
Requires-Dist: wxPython (>=4.2.0)
Requires-Dist: Markdown (>=3.4.1)
Requires-Dist: beautifulsoup4 (>=4.11.2)
